Metadata-Version: 2.1
Name: PyGPT
Version: 1.0.5
Summary: Python implementation of Unofficial ChatGPT Client
Home-page: https://github.com/PawanOsman/PyGPT
Author: Pawan Osman
Author-email: contact@pawan.krd
License: MIT License
License-File: LICENSE
